easydbio/__init__.py
easydbio-0.3.2.dist-info/METADATA
easydbio-0.3.2.dist-info/WHEEL
easydbio-0.3.2.dist-info/top_level.txt
easydbio-0.3.2.dist-info/RECORD
