Metadata-Version: 2.1
Name: easydbio
Version: 0.3.2
Summary: Python module for EasyDB.io
Home-page: https://github.com/EasyDB-io/Python-Client
Author: JakeCooper
Author-email: jake.elijah.cooper@gmail.com
License: UNKNOWN
Platform: UNKNOWN
Classifier: Programming Language :: Python :: 3
Classifier: License :: OSI Approved :: MIT License
Classifier: Operating System :: OS Independent
Requires-Python: >=3.6
